diffdomain/__init__.py
diffdomain/classification.py
diffdomain/diffdomains.py
diffdomain/pydiff.py
diffdomain/utils.py
DiffDomain-0.0.8.dist-info/LICENSE
DiffDomain-0.0.8.dist-info/METADATA
DiffDomain-0.0.8.dist-info/WHEEL
DiffDomain-0.0.8.dist-info/top_level.txt
DiffDomain-0.0.8.dist-info/RECORD
